process_improve/__init__.py
process_improve/batch/__init__.py
process_improve/batch/alignment_helpers.py
process_improve/batch/data_input.py
process_improve/batch/features.py
process_improve/batch/plotting.py
process_improve/batch/preprocessing.py
process_improve/bivariate/__init__.py
process_improve/bivariate/methods.py
process_improve/datasets/batch/batch-fake-data.csv
process_improve/datasets/batch/details.txt
process_improve/datasets/batch/dryer.csv
process_improve/datasets/batch/nylon.csv
process_improve/datasets/experiments/test_doe1.csv
process_improve/datasets/monitoring/batch-yield-and-purity.csv
process_improve/datasets/monitoring/rubber-colour.csv
process_improve/datasets/multivariate/kamyr.csv
process_improve/datasets/multivariate/tablet-spectra.csv
process_improve/datasets/multivariate/LDPE/C.csv
process_improve/datasets/multivariate/LDPE/Hotellings_T2_A3.csv
process_improve/datasets/multivariate/LDPE/Hotellings_T2_A6.csv
process_improve/datasets/multivariate/LDPE/LDPE.csv
process_improve/datasets/multivariate/LDPE/P.csv
process_improve/datasets/multivariate/LDPE/R.csv
process_improve/datasets/multivariate/LDPE/T.csv
process_improve/datasets/multivariate/LDPE/U.csv
process_improve/datasets/multivariate/LDPE/W.csv
process_improve/datasets/multivariate/LDPE/Yhat_A6.csv
process_improve/datasets/multivariate/tpls-pyphi/SOURCE
process_improve/datasets/multivariate/tpls-pyphi/formulas_Group1.csv
process_improve/datasets/multivariate/tpls-pyphi/formulas_Group2.csv
process_improve/datasets/multivariate/tpls-pyphi/formulas_Group3.csv
process_improve/datasets/multivariate/tpls-pyphi/formulas_Group4.csv
process_improve/datasets/multivariate/tpls-pyphi/formulas_Group5.csv
process_improve/datasets/multivariate/tpls-pyphi/process_conditions.csv
process_improve/datasets/multivariate/tpls-pyphi/properties_Group1.csv
process_improve/datasets/multivariate/tpls-pyphi/properties_Group2.csv
process_improve/datasets/multivariate/tpls-pyphi/properties_Group3.csv
process_improve-0.9.865.dist-info/METADATA
process_improve-0.9.865.dist-info/WHEEL
process_improve-0.9.865.dist-info/licenses/LICENSE
process_improve-0.9.865.dist-info/RECORD
