Metadata-Version: 2.4
Name: process-improve
Version: 0.9.865
Summary: Designed Experiments; Latent Variables (PCA, PLS, multivariate methods with missing data); Process Monitoring; Batch data analysis.
Project-URL: Homepage, https://github.com/kgdunn/process_improve
Project-URL: Repository, https://github.com/kgdunn/process_improve
Project-URL: Issues, https://github.com/kgdunn/process_improve/issues
Author-email: Kevin Dunn <kgdunn@gmail.com>
License: MIT license
License-File: LICENSE
Keywords: Batch data analysis,Designed Experiments,Latent Variables,Multivariate Data Analysis,PCA,PLS
Requires-Python: >=3.11
Requires-Dist: bokeh>=3.6.3
Requires-Dist: matplotlib>=3.10.0
Requires-Dist: numba>=0.61.0
Requires-Dist: numpy>=1.26.4
Requires-Dist: openpyxl>=3.1.5
Requires-Dist: pandas>=2.2.3
Requires-Dist: patsy>=1.0.1
Requires-Dist: plotly>=6.0.0
Requires-Dist: pydantic>=2.10.6
Requires-Dist: scikit-image>=0.25.2
Requires-Dist: scikit-learn>=1.6.1
Requires-Dist: scipy<=1.15.3
Requires-Dist: seaborn>=0.13.2
Requires-Dist: statsmodels>=0.14.4
Requires-Dist: tqdm>=4.67.1
